{
  "project" : {
    "id" : "inara_dlya_sts-1000039011-AxX",
    "name" : "inara_dlya_sts-1000039011-AxX",
    "folder" : "/jaicp"
  },
  "settings" : {
    "language" : "ru",
    "spellingCorrection" : false,
    "classificationAlgorithm" : "sts",
    "timezone" : "Europe/Moscow",
    "extendedSettings" : {
      "tokenizerEngine" : "mystem",
      "allowedPatterns" : [ ],
      "useShared" : false
    },
    "shared" : false
  },
  "intents" : [ {
    "path" : "/ГдеНомерЛС",
    "enabled" : true,
    "shared" : false,
    "phrases" : [ {
      "text" : "куда смотреть "
    }, {
      "text" : "где он"
    }, {
      "text" : "где можно посмотреть"
    }, {
      "text" : "где я его возьму"
    } ],
    "classificationRules" : {
      "refs" : [ ]
    },
    "patterns" : [ ],
    "priority" : 0
  }, {
    "path" : "/Онлайн",
    "enabled" : true,
    "shared" : false,
    "phrases" : [ {
      "text" : "онлайн"
    }, {
      "text" : "через интернет"
    }, {
      "text" : "по сети"
    }, {
      "text" : "из дома"
    }, {
      "text" : "удаленно"
    }, {
      "text" : "по компьютеру"
    }, {
      "text" : "через компьютер"
    }, {
      "text" : "через смартфон"
    }, {
      "text" : "по смартфону"
    }, {
      "text" : "сделаю сам"
    }, {
      "text" : "самостоятельно"
    }, {
      "text" : "хочу самостоятельно"
    }, {
      "text" : "сам могу"
    } ],
    "classificationRules" : {
      "refs" : [ ]
    },
    "patterns" : [ ],
    "priority" : 0
  }, {
    "path" : "/привет",
    "enabled" : true,
    "shared" : false,
    "phrases" : [ {
      "text" : "привет"
    } ],
    "classificationRules" : {
      "refs" : [ ]
    },
    "priority" : 0
  }, {
    "path" : "/CallTheOperator",
    "enabled" : true,
    "shared" : false,
    "phrases" : [ {
      "text" : "Переведи на оператора"
    }, {
      "text" : "Хочу говорить с человеком"
    }, {
      "text" : "Переведи на живого"
    }, {
      "text" : "переведи на человека"
    }, {
      "text" : "хочу говорить только с живым"
    }, {
      "text" : "не хочу общаться с роботом"
    }, {
      "text" : "не робот"
    } ],
    "classificationRules" : {
      "refs" : [ ]
    },
    "patterns" : [ ],
    "priority" : 0
  }, {
    "path" : "/ChangeAccountPerson",
    "enabled" : true,
    "shared" : false,
    "phrases" : [ {
      "text" : "сменить собственника"
    }, {
      "text" : "сменить с предыдущего владельца на свое имя"
    }, {
      "text" : "изменить владельца"
    }, {
      "text" : "поменять имя в квитанции"
    }, {
      "text" : "купил @Недвижимость поменять имя в квитанции"
    }, {
      "text" : "изменить хозяина в квитанции"
    }, {
      "text" : "купил  @Недвижимость сменить собственника"
    }, {
      "text" : "приобрел @Недвижимость  оформить лицевой счет на себя"
    }, {
      "text" : "приходит квитанция на старого хозяина хочу чтобы на меня приходило"
    } ],
    "classificationRules" : {
      "refs" : [ ]
    },
    "patterns" : [ ],
    "priority" : 0
  }, {
    "path" : "/ChangeAccountPersonCount",
    "enabled" : true,
    "shared" : false,
    "phrases" : [ {
      "text" : "изменить число проживающих"
    }, {
      "text" : "поменять количество человек"
    }, {
      "text" : "количество людей изменить"
    }, {
      "text" : "уменьшить количество проживающих"
    }, {
      "text" : "увеличить число людей"
    }, {
      "text" : "число человек в квитанции"
    }, {
      "text" : "уменьшить человек в квитанции"
    }, {
      "text" : "исключить из квитанции @duckling.number человек чтобы приходила на @duckling.number "
    } ],
    "classificationRules" : {
      "refs" : [ ]
    },
    "patterns" : [ ],
    "priority" : 0
  }, {
    "path" : "/Лично",
    "enabled" : true,
    "shared" : false,
    "phrases" : [ {
      "text" : "лично"
    }, {
      "text" : "приду сам"
    }, {
      "text" : "прийду самостоятельно"
    }, {
      "text" : "посещу вас"
    }, {
      "text" : "офлайн"
    }, {
      "text" : "оффлайн"
    }, {
      "text" : "вживую"
    }, {
      "text" : "хочу прийти"
    }, {
      "text" : "хочу придти"
    }, {
      "text" : "не онлайн"
    }, {
      "text" : "я не могу онлайн подать а вот в офис приехать"
    }, {
      "text" : "как в офисе сделать"
    } ],
    "classificationRules" : {
      "refs" : [ ]
    },
    "patterns" : [ ],
    "priority" : 0
  }, {
    "path" : "/DontKnow",
    "enabled" : true,
    "shared" : false,
    "phrases" : [ {
      "text" : "не помню"
    }, {
      "text" : "откуда я знаю"
    }, {
      "text" : "я не знаю"
    } ],
    "classificationRules" : {
      "refs" : [ ]
    },
    "patterns" : [ ],
    "priority" : 0
  }, {
    "path" : "/ЛС_ИнойТипВвода",
    "enabled" : true,
    "shared" : false,
    "phrases" : [ {
      "text" : "а можно по иин"
    }, {
      "text" : "по адресу можете"
    }, {
      "text" : "как по другому можно"
    } ],
    "classificationRules" : {
      "refs" : [ ]
    },
    "patterns" : [ ],
    "priority" : 0
  }, {
    "path" : "/Платеж",
    "enabled" : true,
    "shared" : false,
    "phrases" : [ {
      "text" : "заплатил"
    }, {
      "text" : "оплачено"
    }, {
      "text" : "оплачивать квитанцию"
    }, {
      "text" : "оплатить счет"
    }, {
      "text" : "вернуть платеж"
    }, {
      "text" : "доплатить сумму"
    }, {
      "text" : "информация по платежам"
    } ],
    "classificationRules" : {
      "refs" : [ ]
    },
    "patterns" : [ ],
    "priority" : 0
  } ],
  "entities" : [ {
    "entity" : {
      "name" : "Недвижимость",
      "enabled" : true,
      "shared" : false,
      "type" : "annotation",
      "priority" : 1,
      "noSpelling" : true,
      "noMorph" : false,
      "phoneticSearch" : false,
      "fuzzySearch" : false,
      "client" : false,
      "hidden" : false
    },
    "records" : [ {
      "type" : "synonyms",
      "rule" : [ "Дом" ],
      "value" : ""
    }, {
      "type" : "synonyms",
      "rule" : [ "Офис" ],
      "value" : ""
    }, {
      "type" : "synonyms",
      "rule" : [ "Квартира" ],
      "value" : ""
    }, {
      "type" : "synonyms",
      "rule" : [ "недвижимость" ],
      "value" : ""
    } ]
  } ],
  "enabledSystemEntities" : [ "duckling.number", "duckling.time", "duckling.duration", "duckling.phone-number", "duckling.email", "duckling.url" ],
  "spellerDictionary" : [ ],
  "systemEntities" : [ {
    "name" : "mystem.geo",
    "enabled" : false
  }, {
    "name" : "mystem.persn",
    "enabled" : false
  }, {
    "name" : "mystem.obsc",
    "enabled" : false
  }, {
    "name" : "mystem.patrn",
    "enabled" : false
  }, {
    "name" : "mystem.famn",
    "enabled" : false
  }, {
    "name" : "pymorphy.romn",
    "enabled" : false
  }, {
    "name" : "pymorphy.latn",
    "enabled" : false
  }, {
    "name" : "pymorphy.numb",
    "enabled" : false
  }, {
    "name" : "pymorphy.intg",
    "enabled" : false
  }, {
    "name" : "pymorphy.abbr",
    "enabled" : false
  }, {
    "name" : "pymorphy.name",
    "enabled" : false
  }, {
    "name" : "pymorphy.surn",
    "enabled" : false
  }, {
    "name" : "pymorphy.patr",
    "enabled" : false
  }, {
    "name" : "pymorphy.geox",
    "enabled" : false
  }, {
    "name" : "pymorphy.orgn",
    "enabled" : false
  }, {
    "name" : "duckling.number",
    "version" : "v2",
    "enabled" : true
  }, {
    "name" : "duckling.ordinal",
    "version" : "v2",
    "enabled" : false
  }, {
    "name" : "duckling.amount-of-money",
    "version" : "v2",
    "enabled" : false
  }, {
    "name" : "duckling.distance",
    "version" : "v2",
    "enabled" : false
  }, {
    "name" : "duckling.time",
    "version" : "v2",
    "enabled" : true
  }, {
    "name" : "duckling.date",
    "version" : "v2",
    "enabled" : false
  }, {
    "name" : "duckling.time-of-day",
    "version" : "v2",
    "enabled" : false
  }, {
    "name" : "duckling.duration",
    "version" : "v2",
    "enabled" : true
  }, {
    "name" : "duckling.phone-number",
    "version" : "v2",
    "enabled" : true
  }, {
    "name" : "duckling.email",
    "version" : "v2",
    "enabled" : true
  }, {
    "name" : "duckling.url",
    "version" : "v2",
    "enabled" : true
  }, {
    "name" : "duckling.interval",
    "version" : "v2",
    "enabled" : false
  }, {
    "name" : "mlps-obscene.obscene",
    "enabled" : false
  }, {
    "name" : "zb.datetime",
    "enabled" : false
  }, {
    "name" : "zb.number",
    "enabled" : false
  } ]
}